pyautodiff/__init__.py
pyautodiff/admath.py
pyautodiff/dual.py
pyautodiff/interface.py
pyautodiff/optimizer.py
pyautodiff-0.3.2.dist-info/LICENSE.txt
pyautodiff-0.3.2.dist-info/METADATA
pyautodiff-0.3.2.dist-info/WHEEL
pyautodiff-0.3.2.dist-info/top_level.txt
pyautodiff-0.3.2.dist-info/RECORD
