Metadata-Version: 2.1
Name: pyautodiff
Version: 0.3.2
Summary: A package for automatic differentiation
Home-page: https://github.com/cs207-group2/cs207-FinalProject
Author: Phoebe Wong
Author-email: wong@g.harvard.edu
License: UNKNOWN
Platform: UNKNOWN
Classifier: Programming Language :: Python :: 3
Classifier: License :: OSI Approved :: MIT License
Classifier: Operating System :: OS Independent
